scan_your_trash/__init__.py
scan_your_trash/cli.py
scan_your_trash/demuxer.py
scan_your_trash/reader.py
scan_your_trash/storage.py
scan_your_trash/stream_buffer.py
scan_your_trash-1.0.1.dist-info/METADATA
scan_your_trash-1.0.1.dist-info/WHEEL
scan_your_trash-1.0.1.dist-info/entry_points.txt
scan_your_trash-1.0.1.dist-info/licenses/LICENSE
scan_your_trash-1.0.1.dist-info/RECORD
