Metadata-Version: 2.4
Name: scan_your_trash
Version: 1.0.1
Summary: A tool that extracts samples created using the Scan Your Trash app.
Project-URL: Homepage, https://scanyourtrash.de
Author-email: Max Maton <info@delftsolutions.nl>
License-Expression: MIT
License-File: LICENSE
Classifier: Operating System :: OS Independent
Classifier: Programming Language :: Python :: 3
Requires-Dist: av>=10.0.0
Requires-Dist: boto3>=1.26.27
Requires-Dist: numpy>=1.24.2
Requires-Dist: pillow>=9.4.0
